LICENSE
MANIFEST.in
README.rst
requirements.txt
setup.py
pypay/__init__.py
pypay/api.py
pypay/exceptions.py
pypay/payments.py
pypay.egg-info/PKG-INFO
pypay.egg-info/SOURCES.txt
pypay.egg-info/dependency_links.txt
pypay.egg-info/requires.txt
pypay.egg-info/top_level.txt