Metadata-Version: 1.1
Name: pypay
Version: 0.1.1
Summary: Confirm Paypal payments via PDT and IPN
Home-page: http://bitbucket.org/juddgarratt/pypay
Author: Judd Garratt
Author-email: judd.garratt@gmail.com
License: Apache 2.0
Platform: UNKNOWN
Classifier: Development Status :: 3 - Alpha
Classifier: Intended Audience :: Developers
Classifier: Natural Language :: English
Classifier: License :: OSI Approved :: Apache Software License
Classifier: Programming Language :: Python
Classifier: Programming Language :: Python :: 2.6
Classifier: Programming Language :: Python :: 2.7
Classifier: Programming Language :: Python :: 3
Classifier: Programming Language :: Python :: 3.3
Classifier: Programming Language :: Python :: 3.4
